Workbook

Sheet Dashboard
A1: VIKAS SOUHARDA CO-OP BANK - CAMEL HEALTH DASHBOARD
A2: FY2020-21 to FY2024-25 | Rating 1(Strong)->5(Weak) | Auto-calculated
A5: Component | B5: 2020-21 | C5: 2021-22 | D5: 2022-23 | E5: 2023-24 | F5: 2024-25
A6: Capital (C) | B6: =Scorecard!B5 -> 3 | C6: =Scorecard!C5 -> 2 | D6: =Scorecard!D5 -> 2 | E6: =Scorecard!E5 -> 1 | F6: =Scorecard!F5 -> 2
A7: Asset Quality (A) | B7: =Scorecard!B6 -> 3 | C7: =Scorecard!C6 -> 2 | D7: =Scorecard!D6 -> 1 | E7: =Scorecard!E6 -> 3 | F7: =Scorecard!F6 -> 3
A8: Management (M) | B8: =Scorecard!B7 -> 4 | C8: =Scorecard!C7 -> 3 | D8: =Scorecard!D7 -> 3 | E8: =Scorecard!E7 -> 4 | F8: =Scorecard!F7 -> 4
A9: Earnings (E) | B9: =Scorecard!B8 -> 3 | C9: =Scorecard!C8 -> 3 | D9: =Scorecard!D8 -> 3 | E9: =Scorecard!E8 -> 3 | F9: =Scorecard!F8 -> 3
A10: Liquidity (L) | B10: =Scorecard!B9 -> 2 | C10: =Scorecard!C9 -> 2 | D10: =Scorecard!D9 -> 2 | E10: =Scorecard!E9 -> 2 | F10: =Scorecard!F9 -> 2
A11: COMPOSITE SCORE | B11: =Scorecard!B10 -> 2.95 | C11: =Scorecard!C10 -> 2.35 | D11: =Scorecard!D10 -> 2.1 | E11: =Scorecard!E10 -> 2.55 | F11: =Scorecard!F10 -> 2.75
A12: GRADE | B12: =Scorecard!B11 -> Fair | C12: =Scorecard!C11 -> Satisfactory | D12: =Scorecard!D11 -> Satisfactory | E12: =Scorecard!E11 -> Fair | F12: =Scorecard!F11 -> Fair
A14: KEY ANALYTICAL FINDINGS
A15: 1. Trajectory: health peaked FY2022-23 (Satisfactory) then slid in FY23-24 & FY24-25 - driven by Asset Quality + Management, not Capital.
A16: 2. Capital (C): strongest pillar. CRAR 12.3% -> 15.2% (FY24) then eased to 14.68% as RWA outgrew capital.
A17: 3. Asset Quality (A): swing factor. GNPA improved to 1.83% (FY23) then reversed to 4.86% (FY25); PCR fell 100% -> 62.7%.
A18: 4. RBI divergence (FY22-23): true GNPA ~9.3% vs reported 1.83% - governance red flag; stress test drops FY23 to Fair.
A19: 5. Earnings (E): ROA stable but thin (~0.9%); NIM compressed 3.23% -> 2.52% (FY25) - profit leans on non-interest income.
A20: 6. Management (M): Cost-to-Income stuck 72-74% (ex-FY22-23) - persistent inefficiency, worsening again FY24-25.
A21: 7. Liquidity (L): comfortable & stable (CD 62-67%) but structurally low CASA (~13%) keeps funding costs high.
A23: Bottom line: Adequately capitalised & liquid, but a deteriorating-asset-quality + margin-squeeze story, with an FY22-23 NPA-divergence flag undercutting the reported clean-up.

Sheet Rating_Key
A1: CAMEL Rating Key - Thresholds & Weights
A2: 1=Strong | 2=Satisfactory | 3=Fair | 4=Marginal | 5=Weak. Composite=weighted avg (lower=healthier).
A4: Pillar | B4: Scoring Metric | C4: Direction | D4: Band->1 | E4: Band->2 | F4: Band->3 | G4: Band->4 | H4: Weight
A5: C - Capital Adequacy | B5: CRAR % | C5: Higher | D5: 15 | E5: 13 | F5: 11 | G5: 9 | H5: 0.2
A6: A - Asset Quality | B6: Gross NPA % | C6: Lower | D6: 2 | E6: 4 | F6: 6 | G6: 9 | H6: 0.25
A7: M - Management | B7: Cost-to-Income % | C7: Lower | D7: 45 | E7: 55 | F7: 65 | G7: 75 | H7: 0.15
A8: E - Earnings | B8: Return on Assets % | C8: Higher | D8: 1.5 | E8: 1 | F8: 0.75 | G8: 0.5 | H8: 0.2
A9: L - Liquidity | B9: Credit-Deposit Ratio % | C9: Lower | D9: 60 | E9: 68 | F9: 75 | G9: 85 | H9: 0.2
G10: Total | H10: =SUM(H5:H9) -> 1
A12: Grade: <=1.5 Strong | <=2.5 Satisfactory | <=3.5 Fair | <=4.5 Marginal | >4.5 Weak
A13: Edit yellow weights/bands to run scenarios - all sheets recalculate.

Sheet Inputs
A1: Vikas Souharda Co-op Bank - CAMEL Input Ratios (FY2020-21 to FY2024-25)
A2: All %. Blue=editable inputs. * = scoring driver.
A4: Metric | B4: 2020-21 | C4: 2021-22 | D4: 2022-23 | E4: 2023-24 | F4: 2024-25 | G4: Note
A5: * CRAR % | B5: 12.3 | C5: 13.02 | D5: 13.88 | E5: 15.2 | F5: 14.68 | G5: C driver. FY25 audited 14.68 (KPI page 14.98).
A6: Tier 1 Ratio % | B6: 10.99 | C6: 11.81 | D6: 13.35 | E6: 13.35 | F6: 13.35 | G6: Info.
A7: * Gross NPA % | B7: 4.03 | C7: 2.85 | D7: 1.83 | E7: 4.29 | F7: 4.86 | G7: A driver. FY23 pre-RBI-divergence.
A8: Net NPA % | B8: 1.96 | C8: 0.46 | D8: 0 | E8: 0.89 | F8: 1.87 | G8: FY23 floored at 0 (reported -1.19).
A9: Provision Coverage % | B9: 51 | C9: 100 | D9: 100 | E9: 80 | F9: 62.7 | G9: PCR slid FY24->25.
A10: * Cost-to-Income % | B10: 73.8 | C10: 61.8 | D10: 64.4 | E10: 74.4 | F10: 72.2 | G10: M driver. OpEx/(NII+OtherInc), standardised all yrs.
A11: * Return on Assets % | B11: 0.97 | C11: 0.82 | D11: 0.91 | E11: 0.92 | F11: 0.87 | G11: E driver.
A12: Net Interest Margin % | B12: 2.89 | C12: 2.8 | D12: 4.76 | E12: 3.23 | F12: 2.52 | G12: FY23 4.76 outlier - excluded from score.
A13: * Credit-Deposit Ratio % | B13: 62.3 | C13: 62.7 | D13: 65.2 | E13: 67.1 | F13: 63 | G13: L driver.
A14: CASA Ratio % | B14: 13.91 | C14: 13.72 | D14: 13.82 | E14: 12.58 | F14: n/a | G14: Structurally low ~13-14%.
A16: Data-quality flags:
A17: - FY2022-23 RBI divergence: reported GNPA 1.83% (Rs 8.39 Cr) vs RBI-assessed ~9.3% (Rs 42.53 Cr); adj PAT 7.43->5.18 Cr.
A18: - All Rs-figures normalised to Rs Crore before deriving ratios.
A19: - Cost-to-Income standardised to OpEx/(NII+Other income).

Sheet Scorecard
A1: CAMEL Scorecard - Component Ratings & Weighted Composite
A2: Auto-calculated from Inputs vs Rating_Key. 1=Strong ... 5=Weak.
A4: Pillar / Metric | B4: 2020-21 | C4: 2021-22 | D4: 2022-23 | E4: 2023-24 | F4: 2024-25
A5: C - Capital Adequacy (CRAR %) | B5: =IF(Inputs!B5>=Rating_Key!$D$5,1,IF(Inputs!B5>=Rating_Key!$E$5,2,IF(Inputs!B5>=Rating_Key!$F$5,3,IF(Inputs!B5>=Rating_Key!$G$5,4,5)))) -> 3 | C5: =IF(Inputs!C5>=Rating_Key!$D$5,1,IF(Inputs!C5>=Rating_Key!$E$5,2,IF(Inputs!C5>=Rating_Key!$F$5,3,IF(Inputs!C5>=Rating_Key!$G$5,4,5)))) -> 2 | D5: =IF(Inputs!D5>=Rating_Key!$D$5,1,IF(Inputs!D5>=Rating_Key!$E$5,2,IF(Inputs!D5>=Rating_Key!$F$5,3,IF(Inputs!D5>=Rating_Key!$G$5,4,5)))) -> 2 | E5: =IF(Inputs!E5>=Rating_Key!$D$5,1,IF(Inputs!E5>=Rating_Key!$E$5,2,IF(Inputs!E5>=Rating_Key!$F$5,3,IF(Inputs!E5>=Rating_Key!$G$5,4,5)))) -> 1 | F5: =IF(Inputs!F5>=Rating_Key!$D$5,1,IF(Inputs!F5>=Rating_Key!$E$5,2,IF(Inputs!F5>=Rating_Key!$F$5,3,IF(Inputs!F5>=Rating_Key!$G$5,4,5)))) -> 2
A6: A - Asset Quality (Gross NPA %) | B6: =IF(Inputs!B7<=Rating_Key!$D$6,1,IF(Inputs!B7<=Rating_Key!$E$6,2,IF(Inputs!B7<=Rating_Key!$F$6,3,IF(Inputs!B7<=Rating_Key!$G$6,4,5)))) -> 3 | C6: =IF(Inputs!C7<=Rating_Key!$D$6,1,IF(Inputs!C7<=Rating_Key!$E$6,2,IF(Inputs!C7<=Rating_Key!$F$6,3,IF(Inputs!C7<=Rating_Key!$G$6,4,5)))) -> 2 | D6: =IF(Inputs!D7<=Rating_Key!$D$6,1,IF(Inputs!D7<=Rating_Key!$E$6,2,IF(Inputs!D7<=Rating_Key!$F$6,3,IF(Inputs!D7<=Rating_Key!$G$6,4,5)))) -> 1 | E6: =IF(Inputs!E7<=Rating_Key!$D$6,1,IF(Inputs!E7<=Rating_Key!$E$6,2,IF(Inputs!E7<=Rating_Key!$F$6,3,IF(Inputs!E7<=Rating_Key!$G$6,4,5)))) -> 3 | F6: =IF(Inputs!F7<=Rating_Key!$D$6,1,IF(Inputs!F7<=Rating_Key!$E$6,2,IF(Inputs!F7<=Rating_Key!$F$6,3,IF(Inputs!F7<=Rating_Key!$G$6,4,5)))) -> 3
A7: M - Management (Cost-to-Income %) | B7: =IF(Inputs!B10<=Rating_Key!$D$7,1,IF(Inputs!B10<=Rating_Key!$E$7,2,IF(Inputs!B10<=Rating_Key!$F$7,3,IF(Inputs!B10<=Rating_Key!$G$7,4,5)))) -> 4 | C7: =IF(Inputs!C10<=Rating_Key!$D$7,1,IF(Inputs!C10<=Rating_Key!$E$7,2,IF(Inputs!C10<=Rating_Key!$F$7,3,IF(Inputs!C10<=Rating_Key!$G$7,4,5)))) -> 3 | D7: =IF(Inputs!D10<=Rating_Key!$D$7,1,IF(Inputs!D10<=Rating_Key!$E$7,2,IF(Inputs!D10<=Rating_Key!$F$7,3,IF(Inputs!D10<=Rating_Key!$G$7,4,5)))) -> 3 | E7: =IF(Inputs!E10<=Rating_Key!$D$7,1,IF(Inputs!E10<=Rating_Key!$E$7,2,IF(Inputs!E10<=Rating_Key!$F$7,3,IF(Inputs!E10<=Rating_Key!$G$7,4,5)))) -> 4 | F7: =IF(Inputs!F10<=Rating_Key!$D$7,1,IF(Inputs!F10<=Rating_Key!$E$7,2,IF(Inputs!F10<=Rating_Key!$F$7,3,IF(Inputs!F10<=Rating_Key!$G$7,4,5)))) -> 4
A8: E - Earnings (ROA %) | B8: =IF(Inputs!B11>=Rating_Key!$D$8,1,IF(Inputs!B11>=Rating_Key!$E$8,2,IF(Inputs!B11>=Rating_Key!$F$8,3,IF(Inputs!B11>=Rating_Key!$G$8,4,5)))) -> 3 | C8: =IF(Inputs!C11>=Rating_Key!$D$8,1,IF(Inputs!C11>=Rating_Key!$E$8,2,IF(Inputs!C11>=Rating_Key!$F$8,3,IF(Inputs!C11>=Rating_Key!$G$8,4,5)))) -> 3 | D8: =IF(Inputs!D11>=Rating_Key!$D$8,1,IF(Inputs!D11>=Rating_Key!$E$8,2,IF(Inputs!D11>=Rating_Key!$F$8,3,IF(Inputs!D11>=Rating_Key!$G$8,4,5)))) -> 3 | E8: =IF(Inputs!E11>=Rating_Key!$D$8,1,IF(Inputs!E11>=Rating_Key!$E$8,2,IF(Inputs!E11>=Rating_Key!$F$8,3,IF(Inputs!E11>=Rating_Key!$G$8,4,5)))) -> 3 | F8: =IF(Inputs!F11>=Rating_Key!$D$8,1,IF(Inputs!F11>=Rating_Key!$E$8,2,IF(Inputs!F11>=Rating_Key!$F$8,3,IF(Inputs!F11>=Rating_Key!$G$8,4,5)))) -> 3
A9: L - Liquidity (CD Ratio %) | B9: =IF(Inputs!B13<=Rating_Key!$D$9,1,IF(Inputs!B13<=Rating_Key!$E$9,2,IF(Inputs!B13<=Rating_Key!$F$9,3,IF(Inputs!B13<=Rating_Key!$G$9,4,5)))) -> 2 | C9: =IF(Inputs!C13<=Rating_Key!$D$9,1,IF(Inputs!C13<=Rating_Key!$E$9,2,IF(Inputs!C13<=Rating_Key!$F$9,3,IF(Inputs!C13<=Rating_Key!$G$9,4,5)))) -> 2 | D9: =IF(Inputs!D13<=Rating_Key!$D$9,1,IF(Inputs!D13<=Rating_Key!$E$9,2,IF(Inputs!D13<=Rating_Key!$F$9,3,IF(Inputs!D13<=Rating_Key!$G$9,4,5)))) -> 2 | E9: =IF(Inputs!E13<=Rating_Key!$D$9,1,IF(Inputs!E13<=Rating_Key!$E$9,2,IF(Inputs!E13<=Rating_Key!$F$9,3,IF(Inputs!E13<=Rating_Key!$G$9,4,5)))) -> 2 | F9: =IF(Inputs!F13<=Rating_Key!$D$9,1,IF(Inputs!F13<=Rating_Key!$E$9,2,IF(Inputs!F13<=Rating_Key!$F$9,3,IF(Inputs!F13<=Rating_Key!$G$9,4,5)))) -> 2
A10: Weighted Composite Score | B10: =SUMPRODUCT(B5:B9,Rating_Key!$H$5:$H$9) -> 2.95 | C10: =SUMPRODUCT(C5:C9,Rating_Key!$H$5:$H$9) -> 2.35 | D10: =SUMPRODUCT(D5:D9,Rating_Key!$H$5:$H$9) -> 2.1 | E10: =SUMPRODUCT(E5:E9,Rating_Key!$H$5:$H$9) -> 2.55 | F10: =SUMPRODUCT(F5:F9,Rating_Key!$H$5:$H$9) -> 2.75
A11: Composite Grade | B11: =IF(B10<=1.5,"Strong",IF(B10<=2.5,"Satisfactory",IF(B10<=3.5,"Fair",IF(B10<=4.5,"Marginal","Weak")))) -> Fair | C11: =IF(C10<=1.5,"Strong",IF(C10<=2.5,"Satisfactory",IF(C10<=3.5,"Fair",IF(C10<=4.5,"Marginal","Weak")))) -> Satisfactory | D11: =IF(D10<=1.5,"Strong",IF(D10<=2.5,"Satisfactory",IF(D10<=3.5,"Fair",IF(D10<=4.5,"Marginal","Weak")))) -> Satisfactory | E11: =IF(E10<=1.5,"Strong",IF(E10<=2.5,"Satisfactory",IF(E10<=3.5,"Fair",IF(E10<=4.5,"Marginal","Weak")))) -> Fair | F11: =IF(F10<=1.5,"Strong",IF(F10<=2.5,"Satisfactory",IF(F10<=3.5,"Fair",IF(F10<=4.5,"Marginal","Weak")))) -> Fair
A14: Stress test - FY2022-23 RBI-adjusted GNPA 9.3%:
A15: A-pillar (adjusted) | D15: =IF(9.3<=Rating_Key!$D$6,1,IF(9.3<=Rating_Key!$E$6,2,IF(9.3<=Rating_Key!$F$6,3,IF(9.3<=Rating_Key!$G$6,4,5)))) -> 5
A16: Composite (FY23 adj.) | D16: =D5*Rating_Key!$H$5+D15*Rating_Key!$H$6+D7*Rating_Key!$H$7+D8*Rating_Key!$H$8+D9*Rating_Key!$H$9 -> 3.1

Sheet PowerBI_Data
A1: Power BI Fact Table - one row per Year x Pillar (import this sheet)
A3: Financial_Year | B3: Pillar_Code | C3: Pillar_Name | D3: Scoring_Metric | E3: Metric_Value | F3: Component_Rating | G3: Rating_Weight | H3: Weighted_Contribution | I3: Year_Composite | J3: Composite_Grade
A4: 2020-21 | B4: C | C4: Capital Adequacy | D4: CRAR % | E4: =Inputs!B5 -> 12.3 | F4: =Scorecard!B5 -> 3 | G4: =Rating_Key!$H$5 -> 0.2 | H4: =Scorecard!B5*Rating_Key!$H$5 -> 0.6 | I4: =Scorecard!B10 -> 2.95 | J4: =Scorecard!B11 -> Fair
A5: 2020-21 | B5: A | C5: Asset Quality | D5: Gross NPA % | E5: =Inputs!B7 -> 4.03 | F5: =Scorecard!B6 -> 3 | G5: =Rating_Key!$H$6 -> 0.25 | H5: =Scorecard!B6*Rating_Key!$H$6 -> 0.75 | I5: =Scorecard!B10 -> 2.95 | J5: =Scorecard!B11 -> Fair
A6: 2020-21 | B6: M | C6: Management | D6: Cost-to-Income % | E6: =Inputs!B10 -> 73.8 | F6: =Scorecard!B7 -> 4 | G6: =Rating_Key!$H$7 -> 0.15 | H6: =Scorecard!B7*Rating_Key!$H$7 -> 0.6 | I6: =Scorecard!B10 -> 2.95 | J6: =Scorecard!B11 -> Fair
A7: 2020-21 | B7: E | C7: Earnings | D7: Return on Assets % | E7: =Inputs!B11 -> 0.97 | F7: =Scorecard!B8 -> 3 | G7: =Rating_Key!$H$8 -> 0.2 | H7: =Scorecard!B8*Rating_Key!$H$8 -> 0.6 | I7: =Scorecard!B10 -> 2.95 | J7: =Scorecard!B11 -> Fair
A8: 2020-21 | B8: L | C8: Liquidity | D8: Credit-Deposit Ratio % | E8: =Inputs!B13 -> 62.3 | F8: =Scorecard!B9 -> 2 | G8: =Rating_Key!$H$9 -> 0.2 | H8: =Scorecard!B9*Rating_Key!$H$9 -> 0.4 | I8: =Scorecard!B10 -> 2.95 | J8: =Scorecard!B11 -> Fair
A9: 2021-22 | B9: C | C9: Capital Adequacy | D9: CRAR % | E9: =Inputs!C5 -> 13.02 | F9: =Scorecard!C5 -> 2 | G9: =Rating_Key!$H$5 -> 0.2 | H9: =Scorecard!C5*Rating_Key!$H$5 -> 0.4 | I9: =Scorecard!C10 -> 2.35 | J9: =Scorecard!C11 -> Satisfactory
A10: 2021-22 | B10: A | C10: Asset Quality | D10: Gross NPA % | E10: =Inputs!C7 -> 2.85 | F10: =Scorecard!C6 -> 2 | G10: =Rating_Key!$H$6 -> 0.25 | H10: =Scorecard!C6*Rating_Key!$H$6 -> 0.5 | I10: =Scorecard!C10 -> 2.35 | J10: =Scorecard!C11 -> Satisfactory
A11: 2021-22 | B11: M | C11: Management | D11: Cost-to-Income % | E11: =Inputs!C10 -> 61.8 | F11: =Scorecard!C7 -> 3 | G11: =Rating_Key!$H$7 -> 0.15 | H11: =Scorecard!C7*Rating_Key!$H$7 -> 0.45 | I11: =Scorecard!C10 -> 2.35 | J11: =Scorecard!C11 -> Satisfactory
A12: 2021-22 | B12: E | C12: Earnings | D12: Return on Assets % | E12: =Inputs!C11 -> 0.82 | F12: =Scorecard!C8 -> 3 | G12: =Rating_Key!$H$8 -> 0.2 | H12: =Scorecard!C8*Rating_Key!$H$8 -> 0.6 | I12: =Scorecard!C10 -> 2.35 | J12: =Scorecard!C11 -> Satisfactory
A13: 2021-22 | B13: L | C13: Liquidity | D13: Credit-Deposit Ratio % | E13: =Inputs!C13 -> 62.7 | F13: =Scorecard!C9 -> 2 | G13: =Rating_Key!$H$9 -> 0.2 | H13: =Scorecard!C9*Rating_Key!$H$9 -> 0.4 | I13: =Scorecard!C10 -> 2.35 | J13: =Scorecard!C11 -> Satisfactory
A14: 2022-23 | B14: C | C14: Capital Adequacy | D14: CRAR % | E14: =Inputs!D5 -> 13.88 | F14: =Scorecard!D5 -> 2 | G14: =Rating_Key!$H$5 -> 0.2 | H14: =Scorecard!D5*Rating_Key!$H$5 -> 0.4 | I14: =Scorecard!D10 -> 2.1 | J14: =Scorecard!D11 -> Satisfactory
A15: 2022-23 | B15: A | C15: Asset Quality | D15: Gross NPA % | E15: =Inputs!D7 -> 1.83 | F15: =Scorecard!D6 -> 1 | G15: =Rating_Key!$H$6 -> 0.25 | H15: =Scorecard!D6*Rating_Key!$H$6 -> 0.25 | I15: =Scorecard!D10 -> 2.1 | J15: =Scorecard!D11 -> Satisfactory
A16: 2022-23 | B16: M | C16: Management | D16: Cost-to-Income % | E16: =Inputs!D10 -> 64.4 | F16: =Scorecard!D7 -> 3 | G16: =Rating_Key!$H$7 -> 0.15 | H16: =Scorecard!D7*Rating_Key!$H$7 -> 0.45 | I16: =Scorecard!D10 -> 2.1 | J16: =Scorecard!D11 -> Satisfactory
A17: 2022-23 | B17: E | C17: Earnings | D17: Return on Assets % | E17: =Inputs!D11 -> 0.91 | F17: =Scorecard!D8 -> 3 | G17: =Rating_Key!$H$8 -> 0.2 | H17: =Scorecard!D8*Rating_Key!$H$8 -> 0.6 | I17: =Scorecard!D10 -> 2.1 | J17: =Scorecard!D11 -> Satisfactory
A18: 2022-23 | B18: L | C18: Liquidity | D18: Credit-Deposit Ratio % | E18: =Inputs!D13 -> 65.2 | F18: =Scorecard!D9 -> 2 | G18: =Rating_Key!$H$9 -> 0.2 | H18: =Scorecard!D9*Rating_Key!$H$9 -> 0.4 | I18: =Scorecard!D10 -> 2.1 | J18: =Scorecard!D11 -> Satisfactory
A19: 2023-24 | B19: C | C19: Capital Adequacy | D19: CRAR % | E19: =Inputs!E5 -> 15.2 | F19: =Scorecard!E5 -> 1 | G19: =Rating_Key!$H$5 -> 0.2 | H19: =Scorecard!E5*Rating_Key!$H$5 -> 0.2 | I19: =Scorecard!E10 -> 2.55 | J19: =Scorecard!E11 -> Fair
A20: 2023-24 | B20: A | C20: Asset Quality | D20: Gross NPA % | E20: =Inputs!E7 -> 4.29 | F20: =Scorecard!E6 -> 3 | G20: =Rating_Key!$H$6 -> 0.25 | H20: =Scorecard!E6*Rating_Key!$H$6 -> 0.75 | I20: =Scorecard!E10 -> 2.55 | J20: =Scorecard!E11 -> Fair
A21: 2023-24 | B21: M | C21: Management | D21: Cost-to-Income % | E21: =Inputs!E10 -> 74.4 | F21: =Scorecard!E7 -> 4 | G21: =Rating_Key!$H$7 -> 0.15 | H21: =Scorecard!E7*Rating_Key!$H$7 -> 0.6 | I21: =Scorecard!E10 -> 2.55 | J21: =Scorecard!E11 -> Fair
A22: 2023-24 | B22: E | C22: Earnings | D22: Return on Assets % | E22: =Inputs!E11 -> 0.92 | F22: =Scorecard!E8 -> 3 | G22: =Rating_Key!$H$8 -> 0.2 | H22: =Scorecard!E8*Rating_Key!$H$8 -> 0.6 | I22: =Scorecard!E10 -> 2.55 | J22: =Scorecard!E11 -> Fair
A23: 2023-24 | B23: L | C23: Liquidity | D23: Credit-Deposit Ratio % | E23: =Inputs!E13 -> 67.1 | F23: =Scorecard!E9 -> 2 | G23: =Rating_Key!$H$9 -> 0.2 | H23: =Scorecard!E9*Rating_Key!$H$9 -> 0.4 | I23: =Scorecard!E10 -> 2.55 | J23: =Scorecard!E11 -> Fair
A24: 2024-25 | B24: C | C24: Capital Adequacy | D24: CRAR % | E24: =Inputs!F5 -> 14.68 | F24: =Scorecard!F5 -> 2 | G24: =Rating_Key!$H$5 -> 0.2 | H24: =Scorecard!F5*Rating_Key!$H$5 -> 0.4 | I24: =Scorecard!F10 -> 2.75 | J24: =Scorecard!F11 -> Fair
A25: 2024-25 | B25: A | C25: Asset Quality | D25: Gross NPA % | E25: =Inputs!F7 -> 4.86 | F25: =Scorecard!F6 -> 3 | G25: =Rating_Key!$H$6 -> 0.25 | H25: =Scorecard!F6*Rating_Key!$H$6 -> 0.75 | I25: =Scorecard!F10 -> 2.75 | J25: =Scorecard!F11 -> Fair
A26: 2024-25 | B26: M | C26: Management | D26: Cost-to-Income % | E26: =Inputs!F10 -> 72.2 | F26: =Scorecard!F7 -> 4 | G26: =Rating_Key!$H$7 -> 0.15 | H26: =Scorecard!F7*Rating_Key!$H$7 -> 0.6 | I26: =Scorecard!F10 -> 2.75 | J26: =Scorecard!F11 -> Fair
A27: 2024-25 | B27: E | C27: Earnings | D27: Return on Assets % | E27: =Inputs!F11 -> 0.87 | F27: =Scorecard!F8 -> 3 | G27: =Rating_Key!$H$8 -> 0.2 | H27: =Scorecard!F8*Rating_Key!$H$8 -> 0.6 | I27: =Scorecard!F10 -> 2.75 | J27: =Scorecard!F11 -> Fair
A28: 2024-25 | B28: L | C28: Liquidity | D28: Credit-Deposit Ratio % | E28: =Inputs!F13 -> 63 | F28: =Scorecard!F9 -> 2 | G28: =Rating_Key!$H$9 -> 0.2 | H28: =Scorecard!F9*Rating_Key!$H$9 -> 0.4 | I28: =Scorecard!F10 -> 2.75 | J28: =Scorecard!F11 -> Fair
A30: Power BI: Get Data > Excel > PowerBI_Data. Matrix: Financial_Year x Pillar_Code, values=Component_Rating, colour 1(green)->5(red). KPI card=Year_Composite.
